[
  {
    "id": 1,
    "title": "Termo Stanley",
    "description": "Termo stanley para tomar mates con capacidad de 1,2L",
    "code": "TS12L",
    "price": 91599,
    "status": true,
    "stock": 10,
    "category": "Bazar",
    "thumbnails": []
  },
  {
    "id": 2,
    "title": "Notebook ASUS VivoBook 15",
    "description": "Procesador i5, 16gb ram y 512gb ssd",
    "code": "NTBKVS5",
    "price": 600000,
    "status": true,
    "stock": 5,
    "category": "Electronica",
    "thumbnails": []
  },
  {
    "id": 3,
    "title": "Notebook HP",
    "description": "Procesador AMD Ryzen 5, 8gb ram y 512gb ssd",
    "code": "NTBHPRZ5",
    "price": 550600,
    "status": true,
    "stock": 5,
    "category": "Electronica",
    "thumbnails": []
  },
  {
    "id": 4,
    "title": "Jarra Stanley 550ml",
    "description": "Jarro ideal para mantener bebidas frescas",
    "code": "JS550ML",
    "price": 25000,
    "status": true,
    "stock": 50,
    "category": "Bazar",
    "thumbnails": []
  },
  {
    "id": 5,
    "title": "Prueba",
    "description": "prueba",
    "code": "prueba",
    "price": 20,
    "status": true,
    "stock": 20,
    "category": "Prueba",
    "thumbnails": []
  },
  {
    "id": 6,
    "title": "Funciona",
    "description": "Funciona",
    "code": "Funciona",
    "price": 10,
    "status": true,
    "stock": 9,
    "category": "funciona",
    "thumbnails": []
  }
]